Kohlrabi-1.0.0.data/scripts/kohlrabi
Kohlrabi-1.0.0.data/scripts/kohlrabi-server.py
Kohlrabi-1.0.0.dist-info/DESCRIPTION.rst
Kohlrabi-1.0.0.dist-info/METADATA
Kohlrabi-1.0.0.dist-info/RECORD
Kohlrabi-1.0.0.dist-info/WHEEL
Kohlrabi-1.0.0.dist-info/metadata.json
Kohlrabi-1.0.0.dist-info/top_level.txt
libkohlrabi/__init__.py
libkohlrabi/kohlrabi.py
libkohlrabi/server.py
libkohlrabi/util.py
libkohlrabi/tasks/__init__.py
libkohlrabi/tasks/base.py
libkohlrabi/tasks/client.py
libkohlrabi/tasks/serverside.py
