Metadata-Version: 2.0
Name: Kohlrabi
Version: 1.0.0
Summary: An asyncio-based task queue.
Home-page: https://github.com/SunDwarf/Kohlrabi
Author: Isaac Dickinson
Author-email: sun@veriny.tf
License: MIT
Platform: UNKNOWN
Classifier: License :: OSI Approved :: MIT License
Classifier: Development Status :: 5 - Production/Stable
Classifier: Programming Language :: Python
Classifier: Programming Language :: Python :: 3
Classifier: Programming Language :: Python :: 3.3
Classifier: Programming Language :: Python :: 3.4
Classifier: Programming Language :: Python :: 3.5
Classifier: Operating System :: POSIX
Classifier: Intended Audience :: Developers
Classifier: Topic :: Software Development
Classifier: Topic :: Software Development :: Libraries
Requires-Dist: aioredis
Requires-Dist: msgpack-python
